mensajes/__init__.py
mensajes/Adios/__init__.py
mensajes/Adios/despedidas.py
mensajes/hola/__init__.py
mensajes/hola/saludos.py
tests/__init__.py
tests/test_hola.py
Mensajes_Josape-6.0.dist-info/LICENSE
Mensajes_Josape-6.0.dist-info/METADATA
Mensajes_Josape-6.0.dist-info/WHEEL
Mensajes_Josape-6.0.dist-info/top_level.txt
Mensajes_Josape-6.0.dist-info/RECORD
